pyshapdf-0.2.1.dist-info/METADATA
pyshapdf-0.2.1.dist-info/WHEEL
pyshapdf/__init__.py
pyshapdf/pyshapdf.cpython-312-x86_64-linux-gnu.so
pyshapdf-0.2.1.dist-info/RECORD
