Metadata-Version: 2.4
Name: pyshapdf
Version: 0.2.1
Classifier: Development Status :: 4 - Beta
Classifier: Intended Audience :: Developers
Classifier: License :: OSI Approved :: GNU General Public License v3 or later (GPLv3+)
Classifier: Programming Language :: Python :: 3
Classifier: Programming Language :: Python :: 3.8
Classifier: Programming Language :: Python :: 3.9
Classifier: Programming Language :: Python :: 3.10
Classifier: Programming Language :: Python :: 3.11
Classifier: Programming Language :: Python :: 3.12
Classifier: Programming Language :: Python :: 3.13
Classifier: Programming Language :: Rust
Classifier: Topic :: Multimedia :: Graphics
Classifier: Topic :: Software Development :: Libraries :: Python Modules
Summary: Python bindings for shapdf - Create Shapes into PDF
Keywords: pdf,shapes,generator,rust,graphics
Author-email: Teddy van Jerry <me@teddy-van-jerry.org>
License: GPL-3.0-or-later
Requires-Python: >=3.8
Project-URL: Homepage, https://shapdf.wqzhao.org
Project-URL: Documentation, https://docs.rs/shapdf
Project-URL: Repository, https://github.com/Teddy-van-Jerry/shapdf
Project-URL: Bug Tracker, https://github.com/Teddy-van-Jerry/shapdf/issues
